{
    "success": true,
    "moreList": [{
            "id": 5,
            "title": "Everything的正确打开方式。",
            "desc": "我在上一篇文章里介绍了Everything，但大多数对 Everything使用还停留在初级阶段。我就介绍几点我现在正在使用的功能。好了,话不多...",
            "imgUrl": "//upload-images.jianshu.io/upload_images/14827476-35438968c3ca1ca0.jpg?imageMogr2/auto-orient/strip|imageView2/1/w/360/h/240"
        },{
            "id": 6,
            "title": "2019年已经过去七周了",
            "desc": "2019年已经过去7周了，时间过得真快呢。不知道你有没有开始为你的新年计划而努力呢？ 我用这本日程本开启了2019年的梦想实现之旅。 这本日程本...",
            "imgUrl": "//upload-images.jianshu.io/upload_images/4714533-4907bafea202b0e1.jpg?imageMogr2/auto-orient/strip|imageView2/1/w/360/h/240"
        },{
            "id": 7,
            "title": "增强Mybatis处理多表查询 我再也不用写VO类!!!",
            "desc": "每当我们辛苦的解决好表与表之间的耦合时（就是解决好表与表之间的字段冗余） ,然后就会发现比较棘手的问题是联表查询困难至极（主要是定义关联类或者定...",
            "imgUrl": "//upload-images.jianshu.io/upload_images/9368544-ce7fff9b74f62527.png?imageMogr2/auto-orient/strip|imageView2/1/w/360/h/240"
        },{
            "id": 8,
            "title": "剧情大反转？陈昱霖妈妈首回应女儿生活奢豪：买的都是几百块钱假货",
            "desc": "2019年1月21日，有网友扒出，吴秀波“出轨门”女主角陈昱霖ins，通过她发表的社交圈和照片，不难看出陈昱霖的日常生活相当奢华。在社交圈里可以...",
            "imgUrl": "//upload-images.jianshu.io/upload_images/12520064-0b891eb33a49f752.jpg?imageMogr2/auto-orient/strip|imageView2/1/w/360/h/240"
        },{
            "id": 9,
            "title": "前世劫今生缘136",
            "desc": "第136章 正聊着，寝殿门打开了，折颜站在门口一脸忧愁。众人心下一凉，深知不妙。 帝君上前一步急切问道：“如何？” 折颜...",
            "imgUrl": "//upload-images.jianshu.io/upload_images/6856154-f3897e9a44ca9c07.jpg?imageMogr2/auto-orient/strip|imageView2/1/w/360/h/240"
    }]
}